MANIFEST.in
setup.py
src/fsqio.pants.contrib.buildgen.jvm.egg-info/PKG-INFO
src/fsqio.pants.contrib.buildgen.jvm.egg-info/SOURCES.txt
src/fsqio.pants.contrib.buildgen.jvm.egg-info/dependency_links.txt
src/fsqio.pants.contrib.buildgen.jvm.egg-info/entry_points.txt
src/fsqio.pants.contrib.buildgen.jvm.egg-info/namespace_packages.txt
src/fsqio.pants.contrib.buildgen.jvm.egg-info/requires.txt
src/fsqio.pants.contrib.buildgen.jvm.egg-info/top_level.txt
src/fsqio.pants.contrib.buildgen.jvm.egg-info/zip-safe
src/pants/__init__.py
src/pants/contrib/__init__.py
src/pants/contrib/buildgen/__init__.py
src/pants/contrib/buildgen/jvm/__init__.py
src/pants/contrib/buildgen/jvm/map_java_exported_symbols.py
src/pants/contrib/buildgen/jvm/map_jvm_symbol_to_source_tree.py
src/pants/contrib/buildgen/jvm/map_third_party_jar_symbols.py
src/pants/contrib/buildgen/jvm/register.py
src/pants/contrib/buildgen/jvm/scalac_buildgen_task_mixin.py
src/pants/contrib/buildgen/jvm/third_party_map_jvm.py
src/pants/contrib/buildgen/jvm/scala/__init__.py
src/pants/contrib/buildgen/jvm/scala/buildgen_scala.py
src/pants/contrib/buildgen/jvm/scala/map_scala_library_used_addresses.py
src/pants/contrib/buildgen/jvm/scala/scala_exported_symbols.py
src/pants/contrib/buildgen/jvm/scala/scala_used_symbols.py