Metadata-Version: 1.1
Name: fsqio.pants.contrib.buildgen.jvm
Version: 1.0.4
Summary: Foursquare's Buildgen Pants plugin for the JVM
Home-page: https://github.com/foursquare/fsqio
Author: UNKNOWN
Author-email: UNKNOWN
License: Apache License, Version 2.0
Platform: UNKNOWN
Classifier: Intended Audience :: Developers
Classifier: License :: OSI Approved :: Apache Software License
Classifier: Operating System :: MacOS :: MacOS X
Classifier: Operating System :: POSIX :: Linux
Classifier: Programming Language :: Python
Classifier: Topic :: Software Development :: Build Tools
Classifier: Topic :: Software Development :: Code Generators
